tests/__init__.py
tests/test_latexrender.py
latexrender/__init__.py
latexrender/template.tex
latexrender-0.3.6.dist-info/WHEEL
latexrender-0.3.6.dist-info/DESCRIPTION.rst
latexrender-0.3.6.dist-info/top_level.txt
latexrender-0.3.6.dist-info/METADATA
latexrender-0.3.6.dist-info/pydist.json
latexrender-0.3.6.dist-info/RECORD
