Metadata-Version: 2.0
Name: latexrender
Version: 0.3.6
Summary: A simple Flask app for rendering latex snippets into images.
Home-page: https://github.com/lpomfrey/latexrender
Author: Luke Pomfrey
Author-email: lpomfrey@gmail.com
License: BSD
Keywords: l,a,t,e,x,r,e,n,d,e,r
Platform: UNKNOWN
Classifier: Development Status :: 2 - Pre-Alpha
Classifier: Intended Audience :: Developers
Classifier: License :: OSI Approved :: BSD License
Classifier: Natural Language :: English
Classifier: Programming Language :: Python :: 2
Classifier: Programming Language :: Python :: 2.7
Classifier: Programming Language :: Python :: 3
Classifier: Programming Language :: Python :: 3.3
Requires-Dist: flask
Requires-Dist: pillow
